bee/__init__.py
bee/bee.py
bee/apm/__init__.py
bee/cache/__init__.py
bee/config/__init__.py
bee/config/_config.py
bee/config/manager.py
bee/config/source.py
bee/data/__init__.py
bee/data/const.py
bee/data/map.py
bee/data/option.py
bee/data/pool.py
bee/data/guid/__init__.py
bee/data/guid/base32hex.py
bee/data/guid/guid.py
bee/db/__init__.py
bee/db/mongo/__init__.py
bee/db/mongo/_mongo.py
bee/db/psd/__init__.py
bee/db/psd/_psd.py
bee/db/psd/builder.py
bee/db/psd/clause.py
bee/db/psd/column.py
bee/db/psd/criteria.py
bee/db/psd/db.py
bee/db/psd/delete.py
bee/db/psd/exector.py
bee/db/psd/insert.py
bee/db/psd/orm.py
bee/db/psd/result.py
bee/db/psd/select.py
bee/db/psd/table.py
bee/db/psd/update.py
bee/db/psd/value.py
bee/db/psd/abbr/__init__.py
bee/db/psd/abbr/abbr.py
bee/db/psd/connection/__init__.py
bee/db/psd/connection/builder.py
bee/db/psd/connection/connection.py
bee/db/psd/connection/mssql.py
bee/db/psd/connection/mysql.py
bee/db/psd/connection/sqlite.py
bee/db/psd/filter/__init__.py
bee/db/psd/provider/__init__.py
bee/db/psd/provider/provider.py
bee/db/psd/proxy/__init__.py
bee/db/redis/__init__.py
bee/db/redis/_redis.py
bee/errors/__init__.py
bee/errors/error.py
bee/ext/__init__.py
bee/ext/files.py
bee/ext/texts/__init__.py
bee/ext/texts/builder.py
bee/log/__init__.py
bee/net/__init__.py
bee/net/rpc/__init__.py
bee/net/rpc/aiotest.py
bee/net/rpc/balancer.py
bee/net/rpc/channel.py
bee/net/rpc/client.py
bee/net/rpc/codec.py
bee/net/rpc/node.py
bee/net/rpc/server.py
bee/net/rpc/transport.py
bee/net/rpc/codecs/__init__.py
bee/net/rpc/codecs/http/__init__.py
bee/net/rpc/codecs/json/__init__.py
bee/net/rpc/codecs/json/json.py
bee/net/rpc/codecs/proto/__init__.py
bee/net/rpc/codecs/proto/msg_pb2.py
bee/net/rpc/codecs/proto/msg_test.py
bee/net/rpc/codecs/proto/proto.py
bee/net/rpc/registry/__init__.py
bee/net/rpc/registry/builder.py
bee/net/rpc/registry/consul_registry.py
bee/net/rpc/registry/consul_test.py
bee/net/rpc/registry/direct_registry.py
py_auxo_bee-0.1.9.dist-info/LICENSE.rst
py_auxo_bee-0.1.9.dist-info/METADATA
py_auxo_bee-0.1.9.dist-info/WHEEL
py_auxo_bee-0.1.9.dist-info/top_level.txt
py_auxo_bee-0.1.9.dist-info/RECORD
