Metadata-Version: 2.1
Name: py-auxo-bee
Version: 0.1.9
Summary: Bee is an all-in-one python framework for simplifying micro service program development.
Home-page: https://github.com/awenhaowenchao/bee
Author: wenchao.hao
Author-email: awenhaowenchao@hotmail.com
License: MIT
Platform: UNKNOWN
Classifier: License :: OSI Approved :: MIT License
Classifier: Programming Language :: Python
Classifier: Programming Language :: Python :: 3
Classifier: Programming Language :: Python :: 3.6
Classifier: Programming Language :: Python :: Implementation :: CPython
Classifier: Programming Language :: Python :: Implementation :: PyPy
Requires-Python: >=3.6.0
Requires-Dist: etcd3 (>=0.10.0)
Requires-Dist: gsocketpool (>=0.1.6)
Requires-Dist: aiohttp (==3.5.4)
Requires-Dist: pymongo (==3.9.0)
Requires-Dist: python-consul (==1.1.0)
Requires-Dist: pyyml (==0.0.2)
Requires-Dist: pyyaml (>=5.1)
Requires-Dist: redis-py-cluster (==2.0.0)
Requires-Dist: redis (<3.1.0,>=3.0.0)
Requires-Dist: protobuf (>=3.6.1)
Requires-Dist: six (>=1.9.0)
Requires-Dist: bytebuffer (>=0.1.2)
Requires-Dist: pymysql (>=0.9.2)
